setup.cfg
setup.py
docs/CREDITS.TXT
docs/INSTALL.txt
docs/LICENSE.GPL
docs/LICENSE.txt
docs/TODO.txt
plonehrm/__init__.py
plonehrm.personaldata.egg-info/PKG-INFO
plonehrm.personaldata.egg-info/SOURCES.txt
plonehrm.personaldata.egg-info/dependency_links.txt
plonehrm.personaldata.egg-info/entry_points.txt
plonehrm.personaldata.egg-info/namespace_packages.txt
plonehrm.personaldata.egg-info/not-zip-safe
plonehrm.personaldata.egg-info/requires.txt
plonehrm.personaldata.egg-info/top_level.txt
plonehrm/personaldata/ChangeLog
plonehrm/personaldata/HISTORY.txt
plonehrm/personaldata/README.txt
plonehrm/personaldata/__init__.py
plonehrm/personaldata/config.py
plonehrm/personaldata/configure.zcml
plonehrm/personaldata/deprecation.zcml
plonehrm/personaldata/interfaces.py
plonehrm/personaldata/permissions.zcml
plonehrm/personaldata/version.txt
plonehrm/personaldata/content/__init__.py
plonehrm/personaldata/content/personaldata.py
plonehrm/personaldata/profiles/default/import_steps.xml
plonehrm/personaldata/profiles/default/personaldata.txt
plonehrm/personaldata/profiles/default/rolemap.xml
plonehrm/personaldata/profiles/default/types.xml
plonehrm/personaldata/profiles/default/types/PersonalData.xml