Metadata-Version: 1.0
Name: plonehrm.personaldata
Version: 2.0.1
Summary: Personal data for Plone HRM
Home-page: http://zestsoftware.nl
Author: Zest Software
Author-email: info@zestsoftware.nl
License: GPL
Platform: UNKNOWN
Classifier: Framework :: Plone
Classifier: Framework :: Zope2
Classifier: Framework :: Zope3
Classifier: Programming Language :: Python
Classifier: Topic :: Software Development :: Libraries :: Python Modules
